{"summaries":[{"symbol":{"__symbol":0,"members":[]},"metadata":{"__symbolic":"class"},"type":{"summaryKind":1,"type":{"reference":{"__symbol":0,"members":[]},"diDeps":[{"isAttribute":false,"isHost":false,"isSelf":false,"isSkipSelf":false,"isOptional":false,"token":{"identifier":{"reference":{"__symbol":1,"members":[]}}}},{"isAttribute":false,"isHost":false,"isSelf":false,"isSkipSelf":false,"isOptional":false,"token":{"identifier":{"reference":{"__symbol":2,"members":[]}}}}],"lifecycleHooks":[]},"isComponent":false,"selector":"split-gutter","inputs":{"order":"order","direction":"direction","size":"size","disabled":"disabled"},"outputs":{},"hostListeners":{},"hostProperties":{},"hostAttributes":{},"providers":[],"viewProviders":[],"queries":[],"viewQueries":[],"entryComponents":[],"changeDetection":null,"template":null}}],"symbols":[{"__symbol":0,"name":"SplitGutterDirective","filePath":"C:/WWW/angular-split/src/splitGutter.directive.d.ts"},{"__symbol":1,"name":"ElementRef","filePath":"C:/WWW/angular-split/node_modules/@angular/core/core.d.ts"},{"__symbol":2,"name":"Renderer","filePath":"C:/WWW/angular-split/node_modules/@angular/core/core.d.ts"}]}